portgeo/__init__.py
portgeo/common.py
portgeo/foliumap.py
portgeo/portgeo.py
portgeo-0.1.0.dist-info/licenses/LICENSE
portgeo-0.1.0.dist-info/METADATA
portgeo-0.1.0.dist-info/WHEEL
portgeo-0.1.0.dist-info/entry_points.txt
portgeo-0.1.0.dist-info/top_level.txt
portgeo-0.1.0.dist-info/RECORD
